pyiec101/__init__.py
pyiec101/iec101api.py
pyiec101/iec101types.py
pyiec101/iec101x64d.dll
pyiec101/iec60870common.py
pyiec101/libx86_64-iec101.so
pyiec101/structureWithEnums.py
pyiec101/tgtcommon.py
pyiec101/tgtdefines.py
pyiec101/tgterrorcodes.py
pyiec101/tgterrorvalues.py
pyiec101/tgtserialtypes.py
pyiec101/tgttypes.py
pyiec101/tests/iec101clienttest.py
pyiec101/tests/iec101servertest.py
pyiec101-21.6.20.dist-info/licenses/LICENSE
pyiec101-21.6.20.dist-info/METADATA
pyiec101-21.6.20.dist-info/WHEEL
pyiec101-21.6.20.dist-info/top_level.txt
pyiec101-21.6.20.dist-info/RECORD
