Metadata-Version: 2.4
Name: pyiec101
Version: 21.6.20
Summary: IEC 60870-5-101 protocol Server and Client Implementation - Python Wrapper for IEC 101 protocol
Home-page: https://www.freyrscada.com/iec-60870-5-101-python.php
Author: FreyrSCADA
Author-email: contact@freyrscada.com
Classifier: Programming Language :: Python :: 3
Classifier: License :: OSI Approved :: MIT License
Classifier: Operating System :: Microsoft :: Windows
Classifier: Operating System :: POSIX :: Linux
License-File: LICENSE
Dynamic: author
Dynamic: author-email
Dynamic: classifier
Dynamic: description
Dynamic: description-content-type
Dynamic: home-page
Dynamic: license-file
Dynamic: summary
